CopySVGTranslation/__init__.py
CopySVGTranslation/text_utils.py
CopySVGTranslation/titles.py
CopySVGTranslation/workflows.py
CopySVGTranslation/extraction/__init__.py
CopySVGTranslation/extraction/extractor.py
CopySVGTranslation/injection/__init__.py
CopySVGTranslation/injection/batch.py
CopySVGTranslation/injection/injector.py
CopySVGTranslation/injection/preparation.py
CopySVGTranslation/injection/utils.py
CopySVGTranslation/nested_analyze/__init__.py
CopySVGTranslation/nested_analyze/find_nested.py
copysvgtranslation-0.1.6.dist-info/METADATA
copysvgtranslation-0.1.6.dist-info/WHEEL
copysvgtranslation-0.1.6.dist-info/RECORD
