Metadata-Version: 2.4
Name: CopySVGTranslation
Version: 0.1.6
Summary: Utilities for extracting and applying translations to multilingual SVG files.
Project-URL: Homepage, https://github.com/MrIbrahem/CopySVGTranslation
Project-URL: Repository, https://github.com/MrIbrahem/CopySVGTranslation
Project-URL: Issues, https://github.com/MrIbrahem/CopySVGTranslation/issues
Author: Ibrahim Qasim
License: MIT
Requires-Python: >=3.10
Requires-Dist: lxml>=4.9
